cquest/__init__.py
cquest/__version__.py
cquest/api.py
cquest/composer.py
cquest/confighandle.py
cquest/loggings.py
cquest/loggings.yaml
cquest/main.py
cquest/mixins.py
cquest/sessions.py
cquest/tests.py
cquest/url.conf
cquest/utils.py
cquest-0.0.5.dist-info/LICENSE
cquest-0.0.5.dist-info/METADATA
cquest-0.0.5.dist-info/WHEEL
cquest-0.0.5.dist-info/top_level.txt
cquest-0.0.5.dist-info/RECORD
