Metadata-Version: 2.1
Name: cquest
Version: 0.0.5
Summary: 快速插入用户数据进行分组请求,全链路自定义数据.
Home-page: https://www.viaviavi.org
Author: 不怕雷的雨
Author-email: viaviavi365@gmail.com
License: AGPL
Platform: UNKNOWN
Classifier: Intended Audience :: Developers
Classifier: Natural Language :: Chinese (Simplified)
Classifier: Programming Language :: Python
Classifier: Programming Language :: Python :: 3
Classifier: Programming Language :: Python :: 3.8
Classifier: Programming Language :: Python :: 3.9
Classifier: Programming Language :: Python :: 3.10
Classifier: Programming Language :: Python :: Implementation :: CPython
Classifier: Programming Language :: Python :: Implementation :: PyPy
Classifier: Topic :: Software Development :: Libraries
Requires-Python: >=3.8.0
License-File: LICENSE
Requires-Dist: certifi
Requires-Dist: chardet
Requires-Dist: charset-normalizer
Requires-Dist: idna
Requires-Dist: jsonpath
Requires-Dist: PyYAML
Requires-Dist: requests
Requires-Dist: urllib3
